picarlo-0.4.5.dist-info/METADATA
picarlo-0.4.5.dist-info/WHEEL
picarlo-0.4.5.dist-info/entry_points.txt
picarlo-0.4.5.dist-info/licenses/LICENSE
picarlo/__init__.py
picarlo/__main__.py
picarlo/_picarlo_rust.cpython-312-x86_64-linux-gnu.so
picarlo/_picarlo_rust.pyi
picarlo/cli.py
picarlo/sim.py
picarlo-0.4.5.dist-info/RECORD
