Metadata-Version: 2.4
Name: picarlo
Version: 0.4.5
Requires-Dist: loguru>=0.7.2
Requires-Dist: typer>=0.13.1
License-File: LICENSE
Summary: Calculate Pi via the Monte Carlo method
Author-email: Hendrik Frentrup <hendrik.frentrup@gmail.com>
Requires-Python: >=3.9
Project-URL: Homepage, https://github.com/hendrikfrentrup/picarlo
Project-URL: Issues, https://github.com/hendrikfrentrup/picarlo/issues
